{
  "generated_at_utc": "2026-05-14T00:17:54.103794+00:00",
  "s2_start_ts": 1776038400,
  "last_complete_midnight_ts": 1778716800,
  "partners": [
    "exponent",
    "kamino",
    "loopscale",
    "raydium",
    "solstice",
    "whirlpool",
    "yield_vault"
  ],
  "partner_totals": {
    "exponent": 2694763.0,
    "kamino": 2818689099.0,
    "loopscale": 197231067.0,
    "raydium": 9023501.0,
    "solstice": 10139936.0,
    "whirlpool": 388604245.0,
    "yield_vault": 127507.0
  },
  "days": [
    {
      "date": "2026-04-13",
      "cumulative": 109324265.0,
      "inflation": 109324265.0,
      "by_partner": {
        "exponent": {
          "cumulative": 3950.0,
          "inflation": 3950.0
        },
        "kamino": {
          "cumulative": 90925450.0,
          "inflation": 90925450.0
        },
        "loopscale": {
          "cumulative": 5332699.0,
          "inflation": 5332699.0
        },
        "raydium": {
          "cumulative": 290527.0,
          "inflation": 290527.0
        },
        "solstice": {
          "cumulative": 223872.0,
          "inflation": 223872.0
        },
        "whirlpool": {
          "cumulative": 12534525.0,
          "inflation": 12534525.0
        },
        "yield_vault": {
          "cumulative": 13241.0,
          "inflation": 13241.0
        }
      }
    },
    {
      "date": "2026-04-14",
      "cumulative": 218794588.0,
      "inflation": 109470323.0,
      "by_partner": {
        "exponent": {
          "cumulative": 7901.0,
          "inflation": 3950.0
        },
        "kamino": {
          "cumulative": 181850900.0,
          "inflation": 90925450.0
        },
        "loopscale": {
          "cumulative": 10680474.0,
          "inflation": 5347775.0
        },
        "raydium": {
          "cumulative": 581060.0,
          "inflation": 290533.0
        },
        "solstice": {
          "cumulative": 581675.0,
          "inflation": 357803.0
        },
        "whirlpool": {
          "cumulative": 25069052.0,
          "inflation": 12534527.0
        },
        "yield_vault": {
          "cumulative": 23527.0,
          "inflation": 10286.0
        }
      }
    },
    {
      "date": "2026-04-15",
      "cumulative": 328267192.0,
      "inflation": 109472604.0,
      "by_partner": {
        "exponent": {
          "cumulative": 11851.0,
          "inflation": 3950.0
        },
        "kamino": {
          "cumulative": 272776350.0,
          "inflation": 90925450.0
        },
        "loopscale": {
          "cumulative": 16031294.0,
          "inflation": 5350820.0
        },
        "raydium": {
          "cumulative": 871599.0,
          "inflation": 290539.0
        },
        "solstice": {
          "cumulative": 940869.0,
          "inflation": 359194.0
        },
        "whirlpool": {
          "cumulative": 37603587.0,
          "inflation": 12534534.0
        },
        "yield_vault": {
          "cumulative": 31642.0,
          "inflation": 8115.0
        }
      }
    },
    {
      "date": "2026-04-16",
      "cumulative": 437938353.0,
      "inflation": 109671161.0,
      "by_partner": {
        "exponent": {
          "cumulative": 15801.0,
          "inflation": 3950.0
        },
        "kamino": {
          "cumulative": 363701799.0,
          "inflation": 90925450.0
        },
        "loopscale": {
          "cumulative": 21584902.0,
          "inflation": 5553607.0
        },
        "raydium": {
          "cumulative": 1162175.0,
          "inflation": 290576.0
        },
        "solstice": {
          "cumulative": 1296608.0,
          "inflation": 355738.0
        },
        "whirlpool": {
          "cumulative": 50138144.0,
          "inflation": 12534557.0
        },
        "yield_vault": {
          "cumulative": 38924.0,
          "inflation": 7282.0
        }
      }
    },
    {
      "date": "2026-04-17",
      "cumulative": 547765390.0,
      "inflation": 109827038.0,
      "by_partner": {
        "exponent": {
          "cumulative": 19751.0,
          "inflation": 3950.0
        },
        "kamino": {
          "cumulative": 454627249.0,
          "inflation": 90925450.0
        },
        "loopscale": {
          "cumulative": 27300159.0,
          "inflation": 5715258.0
        },
        "raydium": {
          "cumulative": 1452751.0,
          "inflation": 290576.0
        },
        "solstice": {
          "cumulative": 1646519.0,
          "inflation": 349911.0
        },
        "whirlpool": {
          "cumulative": 62673000.0,
          "inflation": 12534856.0
        },
        "yield_vault": {
          "cumulative": 45960.0,
          "inflation": 7037.0
        }
      }
    },
    {
      "date": "2026-04-18",
      "cumulative": 657610783.0,
      "inflation": 109845393.0,
      "by_partner": {
        "exponent": {
          "cumulative": 23702.0,
          "inflation": 3950.0
        },
        "kamino": {
          "cumulative": 545552699.0,
          "inflation": 90925450.0
        },
        "loopscale": {
          "cumulative": 33033908.0,
          "inflation": 5733748.0
        },
        "raydium": {
          "cumulative": 1743327.0,
          "inflation": 290576.0
        },
        "solstice": {
          "cumulative": 1995516.0,
          "inflation": 348997.0
        },
        "whirlpool": {
          "cumulative": 75208742.0,
          "inflation": 12535742.0
        },
        "yield_vault": {
          "cumulative": 52890.0,
          "inflation": 6930.0
        }
      }
    },
    {
      "date": "2026-04-19",
      "cumulative": 767454707.0,
      "inflation": 109843924.0,
      "by_partner": {
        "exponent": {
          "cumulative": 27652.0,
          "inflation": 3950.0
        },
        "kamino": {
          "cumulative": 636478149.0,
          "inflation": 90925450.0
        },
        "loopscale": {
          "cumulative": 38767773.0,
          "inflation": 5733865.0
        },
        "raydium": {
          "cumulative": 2033903.0,
          "inflation": 290576.0
        },
        "solstice": {
          "cumulative": 2343318.0,
          "inflation": 347802.0
        },
        "whirlpool": {
          "cumulative": 87744484.0,
          "inflation": 12535742.0
        },
        "yield_vault": {
          "cumulative": 59428.0,
          "inflation": 6538.0
        }
      }
    },
    {
      "date": "2026-04-20",
      "cumulative": 877296516.0,
      "inflation": 109841809.0,
      "by_partner": {
        "exponent": {
          "cumulative": 31602.0,
          "inflation": 3950.0
        },
        "kamino": {
          "cumulative": 727403599.0,
          "inflation": 90925450.0
        },
        "loopscale": {
          "cumulative": 44501922.0,
          "inflation": 5734149.0
        },
        "raydium": {
          "cumulative": 2324479.0,
          "inflation": 290576.0
        },
        "solstice": {
          "cumulative": 2689519.0,
          "inflation": 346201.0
        },
        "whirlpool": {
          "cumulative": 100280226.0,
          "inflation": 12535742.0
        },
        "yield_vault": {
          "cumulative": 65169.0,
          "inflation": 5740.0
        }
      }
    },
    {
      "date": "2026-04-21",
      "cumulative": 987189869.0,
      "inflation": 109893354.0,
      "by_partner": {
        "exponent": {
          "cumulative": 35553.0,
          "inflation": 3950.0
        },
        "kamino": {
          "cumulative": 818329049.0,
          "inflation": 90925450.0
        },
        "loopscale": {
          "cumulative": 50292484.0,
          "inflation": 5790562.0
        },
        "raydium": {
          "cumulative": 2615055.0,
          "inflation": 290576.0
        },
        "solstice": {
          "cumulative": 3031093.0,
          "inflation": 341574.0
        },
        "whirlpool": {
          "cumulative": 112815969.0,
          "inflation": 12535742.0
        },
        "yield_vault": {
          "cumulative": 70668.0,
          "inflation": 5499.0
        }
      }
    },
    {
      "date": "2026-04-22",
      "cumulative": 1097148883.0,
      "inflation": 109959014.0,
      "by_partner": {
        "exponent": {
          "cumulative": 39503.0,
          "inflation": 3950.0
        },
        "kamino": {
          "cumulative": 909254498.0,
          "inflation": 90925450.0
        },
        "loopscale": {
          "cumulative": 56150024.0,
          "inflation": 5857540.0
        },
        "raydium": {
          "cumulative": 2905630.0,
          "inflation": 290576.0
        },
        "solstice": {
          "cumulative": 3371480.0,
          "inflation": 340387.0
        },
        "whirlpool": {
          "cumulative": 125351711.0,
          "inflation": 12535742.0
        },
        "yield_vault": {
          "cumulative": 76037.0,
          "inflation": 5369.0
        }
      }
    },
    {
      "date": "2026-04-23",
      "cumulative": 1207160841.0,
      "inflation": 110011958.0,
      "by_partner": {
        "exponent": {
          "cumulative": 43453.0,
          "inflation": 3950.0
        },
        "kamino": {
          "cumulative": 1000179948.0,
          "inflation": 90925450.0
        },
        "loopscale": {
          "cumulative": 62059620.0,
          "inflation": 5909596.0
        },
        "raydium": {
          "cumulative": 3196206.0,
          "inflation": 290576.0
        },
        "solstice": {
          "cumulative": 3713285.0,
          "inflation": 341805.0
        },
        "whirlpool": {
          "cumulative": 137887453.0,
          "inflation": 12535742.0
        },
        "yield_vault": {
          "cumulative": 80875.0,
          "inflation": 4837.0
        }
      }
    },
    {
      "date": "2026-04-24",
      "cumulative": 1317301754.0,
      "inflation": 110140913.0,
      "by_partner": {
        "exponent": {
          "cumulative": 47403.0,
          "inflation": 3950.0
        },
        "kamino": {
          "cumulative": 1091105398.0,
          "inflation": 90925450.0
        },
        "loopscale": {
          "cumulative": 68097861.0,
          "inflation": 6038241.0
        },
        "raydium": {
          "cumulative": 3486798.0,
          "inflation": 290592.0
        },
        "solstice": {
          "cumulative": 4055401.0,
          "inflation": 342116.0
        },
        "whirlpool": {
          "cumulative": 150423195.0,
          "inflation": 12535742.0
        },
        "yield_vault": {
          "cumulative": 85698.0,
          "inflation": 4823.0
        }
      }
    },
    {
      "date": "2026-04-25",
      "cumulative": 1427445336.0,
      "inflation": 110143582.0,
      "by_partner": {
        "exponent": {
          "cumulative": 51354.0,
          "inflation": 3950.0
        },
        "kamino": {
          "cumulative": 1182030848.0,
          "inflation": 90925450.0
        },
        "loopscale": {
          "cumulative": 74139504.0,
          "inflation": 6041643.0
        },
        "raydium": {
          "cumulative": 3777396.0,
          "inflation": 290598.0
        },
        "solstice": {
          "cumulative": 4396790.0,
          "inflation": 341389.0
        },
        "whirlpool": {
          "cumulative": 162958937.0,
          "inflation": 12535742.0
        },
        "yield_vault": {
          "cumulative": 90507.0,
          "inflation": 4810.0
        }
      }
    },
    {
      "date": "2026-04-26",
      "cumulative": 1537594039.0,
      "inflation": 110148703.0,
      "by_partner": {
        "exponent": {
          "cumulative": 55304.0,
          "inflation": 3950.0
        },
        "kamino": {
          "cumulative": 1272956298.0,
          "inflation": 90925450.0
        },
        "loopscale": {
          "cumulative": 80198027.0,
          "inflation": 6058523.0
        },
        "raydium": {
          "cumulative": 4067994.0,
          "inflation": 290598.0
        },
        "solstice": {
          "cumulative": 4727030.0,
          "inflation": 330240.0
        },
        "whirlpool": {
          "cumulative": 175494679.0,
          "inflation": 12535742.0
        },
        "yield_vault": {
          "cumulative": 94707.0,
          "inflation": 4199.0
        }
      }
    },
    {
      "date": "2026-04-27",
      "cumulative": 1647747738.0,
      "inflation": 110153699.0,
      "by_partner": {
        "exponent": {
          "cumulative": 59254.0,
          "inflation": 3950.0
        },
        "kamino": {
          "cumulative": 1363881748.0,
          "inflation": 90925450.0
        },
        "loopscale": {
          "cumulative": 86264511.0,
          "inflation": 6066484.0
        },
        "raydium": {
          "cumulative": 4358593.0,
          "inflation": 290599.0
        },
        "solstice": {
          "cumulative": 5055562.0,
          "inflation": 328532.0
        },
        "whirlpool": {
          "cumulative": 188030421.0,
          "inflation": 12535742.0
        },
        "yield_vault": {
          "cumulative": 97649.0,
          "inflation": 2943.0
        }
      }
    },
    {
      "date": "2026-04-28",
      "cumulative": 1758105370.0,
      "inflation": 110357632.0,
      "by_partner": {
        "exponent": {
          "cumulative": 63205.0,
          "inflation": 3950.0
        },
        "kamino": {
          "cumulative": 1454807197.0,
          "inflation": 90925450.0
        },
        "loopscale": {
          "cumulative": 92534468.0,
          "inflation": 6269957.0
        },
        "raydium": {
          "cumulative": 4649192.0,
          "inflation": 290599.0
        },
        "solstice": {
          "cumulative": 5385112.0,
          "inflation": 329550.0
        },
        "whirlpool": {
          "cumulative": 200566224.0,
          "inflation": 12535803.0
        },
        "yield_vault": {
          "cumulative": 99973.0,
          "inflation": 2323.0
        }
      }
    },
    {
      "date": "2026-04-29",
      "cumulative": 1868783455.0,
      "inflation": 110678084.0,
      "by_partner": {
        "exponent": {
          "cumulative": 67155.0,
          "inflation": 3950.0
        },
        "kamino": {
          "cumulative": 1545732647.0,
          "inflation": 90925450.0
        },
        "loopscale": {
          "cumulative": 99122636.0,
          "inflation": 6588169.0
        },
        "raydium": {
          "cumulative": 4940579.0,
          "inflation": 291387.0
        },
        "solstice": {
          "cumulative": 5716102.0,
          "inflation": 330990.0
        },
        "whirlpool": {
          "cumulative": 213102032.0,
          "inflation": 12535807.0
        },
        "yield_vault": {
          "cumulative": 102304.0,
          "inflation": 2331.0
        }
      }
    },
    {
      "date": "2026-04-30",
      "cumulative": 1979492575.0,
      "inflation": 110709120.0,
      "by_partner": {
        "exponent": {
          "cumulative": 71105.0,
          "inflation": 3950.0
        },
        "kamino": {
          "cumulative": 1636658097.0,
          "inflation": 90925450.0
        },
        "loopscale": {
          "cumulative": 105739783.0,
          "inflation": 6617147.0
        },
        "raydium": {
          "cumulative": 5232279.0,
          "inflation": 291700.0
        },
        "solstice": {
          "cumulative": 6048740.0,
          "inflation": 332638.0
        },
        "whirlpool": {
          "cumulative": 225637839.0,
          "inflation": 12535807.0
        },
        "yield_vault": {
          "cumulative": 104732.0,
          "inflation": 2428.0
        }
      }
    },
    {
      "date": "2026-05-01",
      "cumulative": 2090212831.0,
      "inflation": 110720256.0,
      "by_partner": {
        "exponent": {
          "cumulative": 75055.0,
          "inflation": 3950.0
        },
        "kamino": {
          "cumulative": 1727583547.0,
          "inflation": 90925450.0
        },
        "loopscale": {
          "cumulative": 112367088.0,
          "inflation": 6627305.0
        },
        "raydium": {
          "cumulative": 5523979.0,
          "inflation": 291700.0
        },
        "solstice": {
          "cumulative": 6382319.0,
          "inflation": 333579.0
        },
        "whirlpool": {
          "cumulative": 238173646.0,
          "inflation": 12535807.0
        },
        "yield_vault": {
          "cumulative": 107196.0,
          "inflation": 2464.0
        }
      }
    },
    {
      "date": "2026-05-02",
      "cumulative": 2201126141.0,
      "inflation": 110913310.0,
      "by_partner": {
        "exponent": {
          "cumulative": 86896.0,
          "inflation": 11841.0
        },
        "kamino": {
          "cumulative": 1818508997.0,
          "inflation": 90925450.0
        },
        "loopscale": {
          "cumulative": 119179362.0,
          "inflation": 6812273.0
        },
        "raydium": {
          "cumulative": 5815679.0,
          "inflation": 291700.0
        },
        "solstice": {
          "cumulative": 6716355.0,
          "inflation": 334036.0
        },
        "whirlpool": {
          "cumulative": 250709454.0,
          "inflation": 12535807.0
        },
        "yield_vault": {
          "cumulative": 109399.0,
          "inflation": 2203.0
        }
      }
    },
    {
      "date": "2026-05-03",
      "cumulative": 2312092522.0,
      "inflation": 110966381.0,
      "by_partner": {
        "exponent": {
          "cumulative": 109392.0,
          "inflation": 22497.0
        },
        "kamino": {
          "cumulative": 1909434447.0,
          "inflation": 90925450.0
        },
        "loopscale": {
          "cumulative": 126035378.0,
          "inflation": 6856016.0
        },
        "raydium": {
          "cumulative": 6107379.0,
          "inflation": 291700.0
        },
        "solstice": {
          "cumulative": 7049782.0,
          "inflation": 333427.0
        },
        "whirlpool": {
          "cumulative": 263245261.0,
          "inflation": 12535807.0
        },
        "yield_vault": {
          "cumulative": 110883.0,
          "inflation": 1484.0
        }
      }
    },
    {
      "date": "2026-05-04",
      "cumulative": 2423122431.0,
      "inflation": 111029909.0,
      "by_partner": {
        "exponent": {
          "cumulative": 180664.0,
          "inflation": 71271.0
        },
        "kamino": {
          "cumulative": 2000359897.0,
          "inflation": 90925450.0
        },
        "loopscale": {
          "cumulative": 132906700.0,
          "inflation": 6871322.0
        },
        "raydium": {
          "cumulative": 6399079.0,
          "inflation": 291700.0
        },
        "solstice": {
          "cumulative": 7382752.0,
          "inflation": 332970.0
        },
        "whirlpool": {
          "cumulative": 275781068.0,
          "inflation": 12535807.0
        },
        "yield_vault": {
          "cumulative": 112272.0,
          "inflation": 1388.0
        }
      }
    },
    {
      "date": "2026-05-05",
      "cumulative": 2534247114.0,
      "inflation": 111124683.0,
      "by_partner": {
        "exponent": {
          "cumulative": 303985.0,
          "inflation": 123321.0
        },
        "kamino": {
          "cumulative": 2091285346.0,
          "inflation": 90925450.0
        },
        "loopscale": {
          "cumulative": 139820483.0,
          "inflation": 6913783.0
        },
        "raydium": {
          "cumulative": 6690778.0,
          "inflation": 291700.0
        },
        "solstice": {
          "cumulative": 7716090.0,
          "inflation": 333338.0
        },
        "whirlpool": {
          "cumulative": 288316876.0,
          "inflation": 12535807.0
        },
        "yield_vault": {
          "cumulative": 113555.0,
          "inflation": 1284.0
        }
      }
    },
    {
      "date": "2026-05-06",
      "cumulative": 2645420124.0,
      "inflation": 111173010.0,
      "by_partner": {
        "exponent": {
          "cumulative": 431347.0,
          "inflation": 127362.0
        },
        "kamino": {
          "cumulative": 2182210796.0,
          "inflation": 90925450.0
        },
        "loopscale": {
          "cumulative": 146778448.0,
          "inflation": 6957965.0
        },
        "raydium": {
          "cumulative": 6982478.0,
          "inflation": 291700.0
        },
        "solstice": {
          "cumulative": 8049294.0,
          "inflation": 333203.0
        },
        "whirlpool": {
          "cumulative": 300852683.0,
          "inflation": 12535807.0
        },
        "yield_vault": {
          "cumulative": 115079.0,
          "inflation": 1523.0
        }
      }
    },
    {
      "date": "2026-05-07",
      "cumulative": 2756782014.0,
      "inflation": 111361890.0,
      "by_partner": {
        "exponent": {
          "cumulative": 567183.0,
          "inflation": 135837.0
        },
        "kamino": {
          "cumulative": 2273136247.0,
          "inflation": 90925450.0
        },
        "loopscale": {
          "cumulative": 153912630.0,
          "inflation": 7134182.0
        },
        "raydium": {
          "cumulative": 7274178.0,
          "inflation": 291700.0
        },
        "solstice": {
          "cumulative": 8385981.0,
          "inflation": 336687.0
        },
        "whirlpool": {
          "cumulative": 313388491.0,
          "inflation": 12535807.0
        },
        "yield_vault": {
          "cumulative": 117305.0,
          "inflation": 2226.0
        }
      }
    },
    {
      "date": "2026-05-08",
      "cumulative": 2868176800.0,
      "inflation": 111394786.0,
      "by_partner": {
        "exponent": {
          "cumulative": 726876.0,
          "inflation": 159692.0
        },
        "kamino": {
          "cumulative": 2364061697.0,
          "inflation": 90925450.0
        },
        "loopscale": {
          "cumulative": 161055328.0,
          "inflation": 7142699.0
        },
        "raydium": {
          "cumulative": 7565878.0,
          "inflation": 291700.0
        },
        "solstice": {
          "cumulative": 8723365.0,
          "inflation": 337385.0
        },
        "whirlpool": {
          "cumulative": 325924298.0,
          "inflation": 12535807.0
        },
        "yield_vault": {
          "cumulative": 119359.0,
          "inflation": 2053.0
        }
      }
    },
    {
      "date": "2026-05-09",
      "cumulative": 2979704677.0,
      "inflation": 111527877.0,
      "by_partner": {
        "exponent": {
          "cumulative": 981662.0,
          "inflation": 254786.0
        },
        "kamino": {
          "cumulative": 2454987146.0,
          "inflation": 90925450.0
        },
        "loopscale": {
          "cumulative": 168225980.0,
          "inflation": 7170652.0
        },
        "raydium": {
          "cumulative": 7857577.0,
          "inflation": 291700.0
        },
        "solstice": {
          "cumulative": 9070247.0,
          "inflation": 346882.0
        },
        "whirlpool": {
          "cumulative": 338460105.0,
          "inflation": 12535807.0
        },
        "yield_vault": {
          "cumulative": 121960.0,
          "inflation": 2601.0
        }
      }
    },
    {
      "date": "2026-05-10",
      "cumulative": 3091307240.0,
      "inflation": 111602563.0,
      "by_partner": {
        "exponent": {
          "cumulative": 1312061.0,
          "inflation": 330399.0
        },
        "kamino": {
          "cumulative": 2545912596.0,
          "inflation": 90925450.0
        },
        "loopscale": {
          "cumulative": 175404270.0,
          "inflation": 7178290.0
        },
        "raydium": {
          "cumulative": 8149269.0,
          "inflation": 291691.0
        },
        "solstice": {
          "cumulative": 9409043.0,
          "inflation": 338796.0
        },
        "whirlpool": {
          "cumulative": 350995913.0,
          "inflation": 12535807.0
        },
        "yield_vault": {
          "cumulative": 124089.0,
          "inflation": 2129.0
        }
      }
    },
    {
      "date": "2026-05-11",
      "cumulative": 3203057470.0,
      "inflation": 111750230.0,
      "by_partner": {
        "exponent": {
          "cumulative": 1727130.0,
          "inflation": 415069.0
        },
        "kamino": {
          "cumulative": 2636838046.0,
          "inflation": 90925450.0
        },
        "loopscale": {
          "cumulative": 182652686.0,
          "inflation": 7248416.0
        },
        "raydium": {
          "cumulative": 8440680.0,
          "inflation": 291411.0
        },
        "solstice": {
          "cumulative": 9742016.0,
          "inflation": 332973.0
        },
        "whirlpool": {
          "cumulative": 363531882.0,
          "inflation": 12535970.0
        },
        "yield_vault": {
          "cumulative": 125030.0,
          "inflation": 942.0
        }
      }
    },
    {
      "date": "2026-05-12",
      "cumulative": 3314747054.0,
      "inflation": 111689585.0,
      "by_partner": {
        "exponent": {
          "cumulative": 2174993.0,
          "inflation": 447863.0
        },
        "kamino": {
          "cumulative": 2727763548.0,
          "inflation": 90925502.0
        },
        "loopscale": {
          "cumulative": 189941574.0,
          "inflation": 7288889.0
        },
        "raydium": {
          "cumulative": 8732091.0,
          "inflation": 291411.0
        },
        "solstice": {
          "cumulative": 9940612.0,
          "inflation": 198597.0
        },
        "whirlpool": {
          "cumulative": 376068064.0,
          "inflation": 12536181.0
        },
        "yield_vault": {
          "cumulative": 126173.0,
          "inflation": 1143.0
        }
      }
    },
    {
      "date": "2026-05-13",
      "cumulative": 3426510119.0,
      "inflation": 111763065.0,
      "by_partner": {
        "exponent": {
          "cumulative": 2694763.0,
          "inflation": 519770.0
        },
        "kamino": {
          "cumulative": 2818689099.0,
          "inflation": 90925551.0
        },
        "loopscale": {
          "cumulative": 197231067.0,
          "inflation": 7289493.0
        },
        "raydium": {
          "cumulative": 9023501.0,
          "inflation": 291411.0
        },
        "solstice": {
          "cumulative": 10139936.0,
          "inflation": 199324.0
        },
        "whirlpool": {
          "cumulative": 388604245.0,
          "inflation": 12536181.0
        },
        "yield_vault": {
          "cumulative": 127507.0,
          "inflation": 1334.0
        }
      }
    }
  ],
  "sources": {
    "reconstructed_through_last_midnight": 3426510119.0,
    "wallet_quests_grand_total_now": 14375504688.0,
    "wallet_quests_grand_total_non_pda": 4517245772.0,
    "pda_excluded_count": 264,
    "pda_excluded_flares": 9858258916.0,
    "note": "Bars represent flares as of each day's 00:00 UTC. Today is in-progress and is omitted until tomorrow's 00:00 UTC. Protocol-PDA wallets are excluded to match Solstice's leaderboard."
  }
}