{
  "generated_at_utc": "2026-05-15T14:58:53.063349+00:00",
  "s2_start_ts": 1776038400,
  "last_complete_midnight_ts": 1778803200,
  "partners": [
    "exponent",
    "kamino",
    "loopscale",
    "raydium",
    "solstice",
    "whirlpool",
    "yield_vault"
  ],
  "partner_totals": {
    "exponent": 20467572636.0,
    "kamino": 2779862928.0,
    "loopscale": 204965249.0,
    "raydium": 1066550756.0,
    "solstice": 6281468.0,
    "whirlpool": 2316001891.0,
    "yield_vault": 329468.0
  },
  "days": [
    {
      "date": "2026-04-13",
      "cumulative": 775536566.0,
      "inflation": 775536566.0,
      "by_partner": {
        "exponent": {
          "cumulative": 577564077.0,
          "inflation": 577564077.0
        },
        "kamino": {
          "cumulative": 86870717.0,
          "inflation": 86870717.0
        },
        "loopscale": {
          "cumulative": 5396980.0,
          "inflation": 5396980.0
        },
        "raydium": {
          "cumulative": 33179973.0,
          "inflation": 33179973.0
        },
        "solstice": {
          "cumulative": 212221.0,
          "inflation": 212221.0
        },
        "whirlpool": {
          "cumulative": 72294599.0,
          "inflation": 72294599.0
        },
        "yield_vault": {
          "cumulative": 18000.0,
          "inflation": 18000.0
        }
      }
    },
    {
      "date": "2026-04-14",
      "cumulative": 1554714388.0,
      "inflation": 779177821.0,
      "by_partner": {
        "exponent": {
          "cumulative": 1158751351.0,
          "inflation": 581187274.0
        },
        "kamino": {
          "cumulative": 173741433.0,
          "inflation": 86870717.0
        },
        "loopscale": {
          "cumulative": 10808749.0,
          "inflation": 5411768.0
        },
        "raydium": {
          "cumulative": 66366462.0,
          "inflation": 33186490.0
        },
        "solstice": {
          "cumulative": 422339.0,
          "inflation": 210117.0
        },
        "whirlpool": {
          "cumulative": 144590232.0,
          "inflation": 72295633.0
        },
        "yield_vault": {
          "cumulative": 33823.0,
          "inflation": 15823.0
        }
      }
    },
    {
      "date": "2026-04-15",
      "cumulative": 2337539423.0,
      "inflation": 782825035.0,
      "by_partner": {
        "exponent": {
          "cumulative": 1743582589.0,
          "inflation": 584831238.0
        },
        "kamino": {
          "cumulative": 260612150.0,
          "inflation": 86870717.0
        },
        "loopscale": {
          "cumulative": 16223501.0,
          "inflation": 5414753.0
        },
        "raydium": {
          "cumulative": 99552951.0,
          "inflation": 33186489.0
        },
        "solstice": {
          "cumulative": 634339.0,
          "inflation": 212000.0
        },
        "whirlpool": {
          "cumulative": 216886170.0,
          "inflation": 72295938.0
        },
        "yield_vault": {
          "cumulative": 47724.0,
          "inflation": 13901.0
        }
      }
    },
    {
      "date": "2026-04-16",
      "cumulative": 3120853433.0,
      "inflation": 783314010.0,
      "by_partner": {
        "exponent": {
          "cumulative": 2328706570.0,
          "inflation": 585123981.0
        },
        "kamino": {
          "cumulative": 347482866.0,
          "inflation": 86870717.0
        },
        "loopscale": {
          "cumulative": 21837014.0,
          "inflation": 5613512.0
        },
        "raydium": {
          "cumulative": 132739727.0,
          "inflation": 33186776.0
        },
        "solstice": {
          "cumulative": 842995.0,
          "inflation": 208656.0
        },
        "whirlpool": {
          "cumulative": 289183365.0,
          "inflation": 72297196.0
        },
        "yield_vault": {
          "cumulative": 60895.0,
          "inflation": 13172.0
        }
      }
    },
    {
      "date": "2026-04-17",
      "cumulative": 3903334568.0,
      "inflation": 782481135.0,
      "by_partner": {
        "exponent": {
          "cumulative": 2912845039.0,
          "inflation": 584138470.0
        },
        "kamino": {
          "cumulative": 434353583.0,
          "inflation": 86870717.0
        },
        "loopscale": {
          "cumulative": 27609030.0,
          "inflation": 5772016.0
        },
        "raydium": {
          "cumulative": 165925161.0,
          "inflation": 33185433.0
        },
        "solstice": {
          "cumulative": 1045888.0,
          "inflation": 202893.0
        },
        "whirlpool": {
          "cumulative": 361481992.0,
          "inflation": 72298627.0
        },
        "yield_vault": {
          "cumulative": 73875.0,
          "inflation": 12980.0
        }
      }
    },
    {
      "date": "2026-04-18",
      "cumulative": 4687477130.0,
      "inflation": 784142562.0,
      "by_partner": {
        "exponent": {
          "cumulative": 3498479807.0,
          "inflation": 585634767.0
        },
        "kamino": {
          "cumulative": 521224299.0,
          "inflation": 86870717.0
        },
        "loopscale": {
          "cumulative": 33399179.0,
          "inflation": 5790149.0
        },
        "raydium": {
          "cumulative": 199193448.0,
          "inflation": 33268288.0
        },
        "solstice": {
          "cumulative": 1247872.0,
          "inflation": 201984.0
        },
        "whirlpool": {
          "cumulative": 433845739.0,
          "inflation": 72363747.0
        },
        "yield_vault": {
          "cumulative": 86785.0,
          "inflation": 12910.0
        }
      }
    },
    {
      "date": "2026-04-19",
      "cumulative": 5474629263.0,
      "inflation": 787152133.0,
      "by_partner": {
        "exponent": {
          "cumulative": 4087095259.0,
          "inflation": 588615452.0
        },
        "kamino": {
          "cumulative": 608095016.0,
          "inflation": 86870717.0
        },
        "loopscale": {
          "cumulative": 39189443.0,
          "inflation": 5790264.0
        },
        "raydium": {
          "cumulative": 232478766.0,
          "inflation": 33285318.0
        },
        "solstice": {
          "cumulative": 1448758.0,
          "inflation": 200886.0
        },
        "whirlpool": {
          "cumulative": 506222658.0,
          "inflation": 72376919.0
        },
        "yield_vault": {
          "cumulative": 99363.0,
          "inflation": 12578.0
        }
      }
    },
    {
      "date": "2026-04-20",
      "cumulative": 6261243769.0,
      "inflation": 786614506.0,
      "by_partner": {
        "exponent": {
          "cumulative": 4675174679.0,
          "inflation": 588079420.0
        },
        "kamino": {
          "cumulative": 694965732.0,
          "inflation": 86870717.0
        },
        "loopscale": {
          "cumulative": 44979983.0,
          "inflation": 5790540.0
        },
        "raydium": {
          "cumulative": 265764167.0,
          "inflation": 33285400.0
        },
        "solstice": {
          "cumulative": 1647983.0,
          "inflation": 199225.0
        },
        "whirlpool": {
          "cumulative": 578600017.0,
          "inflation": 72377359.0
        },
        "yield_vault": {
          "cumulative": 111208.0,
          "inflation": 11845.0
        }
      }
    },
    {
      "date": "2026-04-21",
      "cumulative": 7039289966.0,
      "inflation": 778046198.0,
      "by_partner": {
        "exponent": {
          "cumulative": 5254635713.0,
          "inflation": 579461034.0
        },
        "kamino": {
          "cumulative": 781836449.0,
          "inflation": 86870717.0
        },
        "loopscale": {
          "cumulative": 50825556.0,
          "inflation": 5845572.0
        },
        "raydium": {
          "cumulative": 299049543.0,
          "inflation": 33285376.0
        },
        "solstice": {
          "cumulative": 1842494.0,
          "inflation": 194511.0
        },
        "whirlpool": {
          "cumulative": 650977376.0,
          "inflation": 72377359.0
        },
        "yield_vault": {
          "cumulative": 122836.0,
          "inflation": 11628.0
        }
      }
    },
    {
      "date": "2026-04-22",
      "cumulative": 7817678618.0,
      "inflation": 778388651.0,
      "by_partner": {
        "exponent": {
          "cumulative": 5834375018.0,
          "inflation": 579739306.0
        },
        "kamino": {
          "cumulative": 868707165.0,
          "inflation": 86870717.0
        },
        "loopscale": {
          "cumulative": 56736511.0,
          "inflation": 5910955.0
        },
        "raydium": {
          "cumulative": 332334918.0,
          "inflation": 33285375.0
        },
        "solstice": {
          "cumulative": 2035838.0,
          "inflation": 193344.0
        },
        "whirlpool": {
          "cumulative": 723354816.0,
          "inflation": 72377440.0
        },
        "yield_vault": {
          "cumulative": 134351.0,
          "inflation": 11515.0
        }
      }
    },
    {
      "date": "2026-04-23",
      "cumulative": 8597438308.0,
      "inflation": 779759690.0,
      "by_partner": {
        "exponent": {
          "cumulative": 6415432915.0,
          "inflation": 581057896.0
        },
        "kamino": {
          "cumulative": 955577882.0,
          "inflation": 86870717.0
        },
        "loopscale": {
          "cumulative": 62698070.0,
          "inflation": 5961560.0
        },
        "raydium": {
          "cumulative": 365620292.0,
          "inflation": 33285375.0
        },
        "solstice": {
          "cumulative": 2230683.0,
          "inflation": 194845.0
        },
        "whirlpool": {
          "cumulative": 795733061.0,
          "inflation": 72378244.0
        },
        "yield_vault": {
          "cumulative": 145405.0,
          "inflation": 11053.0
        }
      }
    },
    {
      "date": "2026-04-24",
      "cumulative": 9390309703.0,
      "inflation": 792871395.0,
      "by_partner": {
        "exponent": {
          "cumulative": 7009476887.0,
          "inflation": 594043973.0
        },
        "kamino": {
          "cumulative": 1042448598.0,
          "inflation": 86870717.0
        },
        "loopscale": {
          "cumulative": 68784686.0,
          "inflation": 6086616.0
        },
        "raydium": {
          "cumulative": 398905658.0,
          "inflation": 33285366.0
        },
        "solstice": {
          "cumulative": 2426091.0,
          "inflation": 195407.0
        },
        "whirlpool": {
          "cumulative": 868111338.0,
          "inflation": 72378277.0
        },
        "yield_vault": {
          "cumulative": 156445.0,
          "inflation": 11040.0
        }
      }
    },
    {
      "date": "2026-04-25",
      "cumulative": 10197321799.0,
      "inflation": 807012096.0,
      "by_partner": {
        "exponent": {
          "cumulative": 7617658255.0,
          "inflation": 608181368.0
        },
        "kamino": {
          "cumulative": 1129319315.0,
          "inflation": 86870717.0
        },
        "loopscale": {
          "cumulative": 74874613.0,
          "inflation": 6089927.0
        },
        "raydium": {
          "cumulative": 432191336.0,
          "inflation": 33285678.0
        },
        "solstice": {
          "cumulative": 2620917.0,
          "inflation": 194827.0
        },
        "whirlpool": {
          "cumulative": 940489891.0,
          "inflation": 72378553.0
        },
        "yield_vault": {
          "cumulative": 167472.0,
          "inflation": 11027.0
        }
      }
    },
    {
      "date": "2026-04-26",
      "cumulative": 11008140360.0,
      "inflation": 810818561.0,
      "by_partner": {
        "exponent": {
          "cumulative": 8229641283.0,
          "inflation": 611983028.0
        },
        "kamino": {
          "cumulative": 1216190031.0,
          "inflation": 86870717.0
        },
        "loopscale": {
          "cumulative": 80980974.0,
          "inflation": 6106362.0
        },
        "raydium": {
          "cumulative": 465476986.0,
          "inflation": 33285649.0
        },
        "solstice": {
          "cumulative": 2804677.0,
          "inflation": 183760.0
        },
        "whirlpool": {
          "cumulative": 1012868449.0,
          "inflation": 72378559.0
        },
        "yield_vault": {
          "cumulative": 177959.0,
          "inflation": 10487.0
        }
      }
    },
    {
      "date": "2026-04-27",
      "cumulative": 11853713762.0,
      "inflation": 845573402.0,
      "by_partner": {
        "exponent": {
          "cumulative": 8876374391.0,
          "inflation": 646733108.0
        },
        "kamino": {
          "cumulative": 1303060748.0,
          "inflation": 86870717.0
        },
        "loopscale": {
          "cumulative": 87095036.0,
          "inflation": 6114062.0
        },
        "raydium": {
          "cumulative": 498762551.0,
          "inflation": 33285566.0
        },
        "solstice": {
          "cumulative": 2986661.0,
          "inflation": 181983.0
        },
        "whirlpool": {
          "cumulative": 1085247008.0,
          "inflation": 72378559.0
        },
        "yield_vault": {
          "cumulative": 187366.0,
          "inflation": 9407.0
        }
      }
    },
    {
      "date": "2026-04-28",
      "cumulative": 12722025777.0,
      "inflation": 868312015.0,
      "by_partner": {
        "exponent": {
          "cumulative": 9545652086.0,
          "inflation": 669277695.0
        },
        "kamino": {
          "cumulative": 1389931464.0,
          "inflation": 86870717.0
        },
        "loopscale": {
          "cumulative": 93402547.0,
          "inflation": 6307511.0
        },
        "raydium": {
          "cumulative": 532047892.0,
          "inflation": 33285341.0
        },
        "solstice": {
          "cumulative": 3169682.0,
          "inflation": 183022.0
        },
        "whirlpool": {
          "cumulative": 1157625865.0,
          "inflation": 72378856.0
        },
        "yield_vault": {
          "cumulative": 196240.0,
          "inflation": 8873.0
        }
      }
    },
    {
      "date": "2026-04-29",
      "cumulative": 13594975013.0,
      "inflation": 872949236.0,
      "by_partner": {
        "exponent": {
          "cumulative": 10219250407.0,
          "inflation": 673598321.0
        },
        "kamino": {
          "cumulative": 1476802181.0,
          "inflation": 86870717.0
        },
        "loopscale": {
          "cumulative": 100016650.0,
          "inflation": 6614102.0
        },
        "raydium": {
          "cumulative": 565341317.0,
          "inflation": 33293425.0
        },
        "solstice": {
          "cumulative": 3354185.0,
          "inflation": 184502.0
        },
        "whirlpool": {
          "cumulative": 1230005153.0,
          "inflation": 72379289.0
        },
        "yield_vault": {
          "cumulative": 205119.0,
          "inflation": 8880.0
        }
      }
    },
    {
      "date": "2026-04-30",
      "cumulative": 14463051996.0,
      "inflation": 868076983.0,
      "by_partner": {
        "exponent": {
          "cumulative": 10887942799.0,
          "inflation": 668692392.0
        },
        "kamino": {
          "cumulative": 1563672897.0,
          "inflation": 86870717.0
        },
        "loopscale": {
          "cumulative": 106658564.0,
          "inflation": 6641914.0
        },
        "raydium": {
          "cumulative": 598638743.0,
          "inflation": 33297425.0
        },
        "solstice": {
          "cumulative": 3540375.0,
          "inflation": 186191.0
        },
        "whirlpool": {
          "cumulative": 1302384531.0,
          "inflation": 72379378.0
        },
        "yield_vault": {
          "cumulative": 214086.0,
          "inflation": 8967.0
        }
      }
    },
    {
      "date": "2026-05-01",
      "cumulative": 15329581083.0,
      "inflation": 866529088.0,
      "by_partner": {
        "exponent": {
          "cumulative": 11555076099.0,
          "inflation": 667133300.0
        },
        "kamino": {
          "cumulative": 1650543614.0,
          "inflation": 86870717.0
        },
        "loopscale": {
          "cumulative": 113310227.0,
          "inflation": 6651663.0
        },
        "raydium": {
          "cumulative": 631935931.0,
          "inflation": 33297189.0
        },
        "solstice": {
          "cumulative": 3728062.0,
          "inflation": 187687.0
        },
        "whirlpool": {
          "cumulative": 1374764071.0,
          "inflation": 72379540.0
        },
        "yield_vault": {
          "cumulative": 223078.0,
          "inflation": 8992.0
        }
      }
    },
    {
      "date": "2026-05-02",
      "cumulative": 16206118465.0,
      "inflation": 876537382.0,
      "by_partner": {
        "exponent": {
          "cumulative": 12232043812.0,
          "inflation": 676967713.0
        },
        "kamino": {
          "cumulative": 1737414330.0,
          "inflation": 86870717.0
        },
        "loopscale": {
          "cumulative": 120136252.0,
          "inflation": 6826025.0
        },
        "raydium": {
          "cumulative": 665232723.0,
          "inflation": 33296792.0
        },
        "solstice": {
          "cumulative": 3915927.0,
          "inflation": 187865.0
        },
        "whirlpool": {
          "cumulative": 1447143611.0,
          "inflation": 72379540.0
        },
        "yield_vault": {
          "cumulative": 231809.0,
          "inflation": 8731.0
        }
      }
    },
    {
      "date": "2026-05-03",
      "cumulative": 17083264357.0,
      "inflation": 877145892.0,
      "by_partner": {
        "exponent": {
          "cumulative": 12909579966.0,
          "inflation": 677536154.0
        },
        "kamino": {
          "cumulative": 1824285047.0,
          "inflation": 86870717.0
        },
        "loopscale": {
          "cumulative": 127003584.0,
          "inflation": 6867332.0
        },
        "raydium": {
          "cumulative": 698529510.0,
          "inflation": 33296788.0
        },
        "solstice": {
          "cumulative": 4103163.0,
          "inflation": 187236.0
        },
        "whirlpool": {
          "cumulative": 1519523193.0,
          "inflation": 72379582.0
        },
        "yield_vault": {
          "cumulative": 239893.0,
          "inflation": 8084.0
        }
      }
    },
    {
      "date": "2026-05-04",
      "cumulative": 17963563583.0,
      "inflation": 880299225.0,
      "by_partner": {
        "exponent": {
          "cumulative": 13590128407.0,
          "inflation": 680548441.0
        },
        "kamino": {
          "cumulative": 1911155763.0,
          "inflation": 86870717.0
        },
        "loopscale": {
          "cumulative": 133872229.0,
          "inflation": 6868645.0
        },
        "raydium": {
          "cumulative": 731965607.0,
          "inflation": 33436096.0
        },
        "solstice": {
          "cumulative": 4290931.0,
          "inflation": 187767.0
        },
        "whirlpool": {
          "cumulative": 1591902804.0,
          "inflation": 72379611.0
        },
        "yield_vault": {
          "cumulative": 247841.0,
          "inflation": 7948.0
        }
      }
    },
    {
      "date": "2026-05-05",
      "cumulative": 18844187219.0,
      "inflation": 880623637.0,
      "by_partner": {
        "exponent": {
          "cumulative": 14270963446.0,
          "inflation": 680835039.0
        },
        "kamino": {
          "cumulative": 1998026480.0,
          "inflation": 86870717.0
        },
        "loopscale": {
          "cumulative": 140757505.0,
          "inflation": 6885275.0
        },
        "raydium": {
          "cumulative": 765423394.0,
          "inflation": 33457787.0
        },
        "solstice": {
          "cumulative": 4478290.0,
          "inflation": 187359.0
        },
        "whirlpool": {
          "cumulative": 1664282415.0,
          "inflation": 72379611.0
        },
        "yield_vault": {
          "cumulative": 255690.0,
          "inflation": 7849.0
        }
      }
    },
    {
      "date": "2026-05-06",
      "cumulative": 19723607353.0,
      "inflation": 879420134.0,
      "by_partner": {
        "exponent": {
          "cumulative": 14950554179.0,
          "inflation": 679590733.0
        },
        "kamino": {
          "cumulative": 2084897196.0,
          "inflation": 86870717.0
        },
        "loopscale": {
          "cumulative": 147683865.0,
          "inflation": 6926361.0
        },
        "raydium": {
          "cumulative": 798881157.0,
          "inflation": 33457763.0
        },
        "solstice": {
          "cumulative": 4665188.0,
          "inflation": 186899.0
        },
        "whirlpool": {
          "cumulative": 1736662025.0,
          "inflation": 72379611.0
        },
        "yield_vault": {
          "cumulative": 263741.0,
          "inflation": 8051.0
        }
      }
    },
    {
      "date": "2026-05-07",
      "cumulative": 20602896732.0,
      "inflation": 879289379.0,
      "by_partner": {
        "exponent": {
          "cumulative": 15629843948.0,
          "inflation": 679289769.0
        },
        "kamino": {
          "cumulative": 2171767913.0,
          "inflation": 86870717.0
        },
        "loopscale": {
          "cumulative": 154774171.0,
          "inflation": 7090305.0
        },
        "raydium": {
          "cumulative": 832340326.0,
          "inflation": 33459169.0
        },
        "solstice": {
          "cumulative": 4856208.0,
          "inflation": 191020.0
        },
        "whirlpool": {
          "cumulative": 1809041636.0,
          "inflation": 72379611.0
        },
        "yield_vault": {
          "cumulative": 272529.0,
          "inflation": 8788.0
        }
      }
    },
    {
      "date": "2026-05-08",
      "cumulative": 21483519145.0,
      "inflation": 880622413.0,
      "by_partner": {
        "exponent": {
          "cumulative": 16310457662.0,
          "inflation": 680613714.0
        },
        "kamino": {
          "cumulative": 2258638629.0,
          "inflation": 86870717.0
        },
        "loopscale": {
          "cumulative": 161872243.0,
          "inflation": 7098072.0
        },
        "raydium": {
          "cumulative": 865800333.0,
          "inflation": 33460007.0
        },
        "solstice": {
          "cumulative": 5047742.0,
          "inflation": 191534.0
        },
        "whirlpool": {
          "cumulative": 1881421367.0,
          "inflation": 72379732.0
        },
        "yield_vault": {
          "cumulative": 281168.0,
          "inflation": 8638.0
        }
      }
    },
    {
      "date": "2026-05-09",
      "cumulative": 22372734833.0,
      "inflation": 889215688.0,
      "by_partner": {
        "exponent": {
          "cumulative": 16999628959.0,
          "inflation": 689171296.0
        },
        "kamino": {
          "cumulative": 2345509346.0,
          "inflation": 86870717.0
        },
        "loopscale": {
          "cumulative": 168995810.0,
          "inflation": 7123567.0
        },
        "raydium": {
          "cumulative": 899260720.0,
          "inflation": 33460387.0
        },
        "solstice": {
          "cumulative": 5248425.0,
          "inflation": 200682.0
        },
        "whirlpool": {
          "cumulative": 1953802646.0,
          "inflation": 72381279.0
        },
        "yield_vault": {
          "cumulative": 288928.0,
          "inflation": 7760.0
        }
      }
    },
    {
      "date": "2026-05-10",
      "cumulative": 23256429477.0,
      "inflation": 883694644.0,
      "by_partner": {
        "exponent": {
          "cumulative": 17683280027.0,
          "inflation": 683651068.0
        },
        "kamino": {
          "cumulative": 2432380062.0,
          "inflation": 86870717.0
        },
        "loopscale": {
          "cumulative": 176126200.0,
          "inflation": 7130391.0
        },
        "raydium": {
          "cumulative": 932720835.0,
          "inflation": 33460114.0
        },
        "solstice": {
          "cumulative": 5441557.0,
          "inflation": 193132.0
        },
        "whirlpool": {
          "cumulative": 2026184225.0,
          "inflation": 72381579.0
        },
        "yield_vault": {
          "cumulative": 296571.0,
          "inflation": 7643.0
        }
      }
    },
    {
      "date": "2026-05-11",
      "cumulative": 24150010998.0,
      "inflation": 893581521.0,
      "by_partner": {
        "exponent": {
          "cumulative": 18376758943.0,
          "inflation": 693478916.0
        },
        "kamino": {
          "cumulative": 2519250779.0,
          "inflation": 86870717.0
        },
        "loopscale": {
          "cumulative": 183276141.0,
          "inflation": 7149941.0
        },
        "raydium": {
          "cumulative": 966178315.0,
          "inflation": 33457480.0
        },
        "solstice": {
          "cumulative": 5636521.0,
          "inflation": 194964.0
        },
        "whirlpool": {
          "cumulative": 2098606086.0,
          "inflation": 72421861.0
        },
        "yield_vault": {
          "cumulative": 304213.0,
          "inflation": 7641.0
        }
      }
    },
    {
      "date": "2026-05-12",
      "cumulative": 25047886290.0,
      "inflation": 897875292.0,
      "by_partner": {
        "exponent": {
          "cumulative": 19074450881.0,
          "inflation": 697691938.0
        },
        "kamino": {
          "cumulative": 2606121495.0,
          "inflation": 86870717.0
        },
        "loopscale": {
          "cumulative": 190443841.0,
          "inflation": 7167700.0
        },
        "raydium": {
          "cumulative": 999635795.0,
          "inflation": 33457480.0
        },
        "solstice": {
          "cumulative": 5851510.0,
          "inflation": 214989.0
        },
        "whirlpool": {
          "cumulative": 2171070437.0,
          "inflation": 72464351.0
        },
        "yield_vault": {
          "cumulative": 312330.0,
          "inflation": 8118.0
        }
      }
    },
    {
      "date": "2026-05-13",
      "cumulative": 25943895713.0,
      "inflation": 896009423.0,
      "by_partner": {
        "exponent": {
          "cumulative": 19770200667.0,
          "inflation": 695749785.0
        },
        "kamino": {
          "cumulative": 2692992212.0,
          "inflation": 86870717.0
        },
        "loopscale": {
          "cumulative": 197684969.0,
          "inflation": 7241129.0
        },
        "raydium": {
          "cumulative": 1033093276.0,
          "inflation": 33457480.0
        },
        "solstice": {
          "cumulative": 6067470.0,
          "inflation": 215960.0
        },
        "whirlpool": {
          "cumulative": 2243536164.0,
          "inflation": 72465727.0
        },
        "yield_vault": {
          "cumulative": 320955.0,
          "inflation": 8625.0
        }
      }
    },
    {
      "date": "2026-05-14",
      "cumulative": 26841564396.0,
      "inflation": 897668683.0,
      "by_partner": {
        "exponent": {
          "cumulative": 20467572636.0,
          "inflation": 697371969.0
        },
        "kamino": {
          "cumulative": 2779862928.0,
          "inflation": 86870717.0
        },
        "loopscale": {
          "cumulative": 204965249.0,
          "inflation": 7280279.0
        },
        "raydium": {
          "cumulative": 1066550756.0,
          "inflation": 33457480.0
        },
        "solstice": {
          "cumulative": 6281468.0,
          "inflation": 213998.0
        },
        "whirlpool": {
          "cumulative": 2316001891.0,
          "inflation": 72465727.0
        },
        "yield_vault": {
          "cumulative": 329468.0,
          "inflation": 8513.0
        }
      }
    }
  ],
  "sources": {
    "reconstructed_through_last_midnight": 26841564396.0,
    "wallet_quests_grand_total_now": 40880247082.0,
    "wallet_quests_grand_total_non_pda": 27385196703.0,
    "pda_excluded_count": 264,
    "pda_excluded_flares": 13495050379.0,
    "note": "Bars represent flares as of each day's 00:00 UTC. Today is in-progress and is omitted until tomorrow's 00:00 UTC. Protocol-PDA wallets are excluded to match Solstice's leaderboard."
  }
}