{"wallet":"TxD1RuZpZW14BR1z3bN5zi89doZYQLw4NspEVE9WvEh","meta":{"classification":"unclassified","cohort":null,"is_s1":false,"n_protocols":0,"first_seen_ts":null,"last_active_ts":null,"is_protocol_pda":false,"pda_source":null,"pda_label":null,"pda_protocol_hint":null},"total_flares":3062.146814413922,"by_quest":[{"quest":"S2_HOLD_USX_DAILY","flares":0,"source":null,"updated_at":null},{"quest":"S2_HOLD_USX_1MO","flares":0,"source":null,"updated_at":null},{"quest":"S2_HOLD_USX_3MO","flares":0,"source":null,"updated_at":null},{"quest":"S2_HOLD_EUSX_DAILY","flares":0,"source":null,"updated_at":null},{"quest":"S2_HOLD_EUSX_1MO","flares":0,"source":null,"updated_at":null},{"quest":"S2_HOLD_EUSX_3MO","flares":0,"source":null,"updated_at":null},{"quest":"S2_EXPONENT_YIELD_USX_JUN26","flares":0,"source":null,"updated_at":null},{"quest":"S2_EXPONENT_YIELD_EUSX_JUN26","flares":0,"source":null,"updated_at":null},{"quest":"S2_EXPONENT_LP_USX_JUN26","flares":0,"source":null,"updated_at":null},{"quest":"S2_EXPONENT_LP_EUSX_JUN26","flares":0,"source":null,"updated_at":null},{"quest":"S2_KAMINO_LEND_USX","flares":0,"source":null,"updated_at":null},{"quest":"S2_KAMINO_LEND_EUSX","flares":0,"source":null,"updated_at":null},{"quest":"S2_KAMINO_LEND_USDG","flares":0,"source":null,"updated_at":null},{"quest":"S2_KAMINO_BORROW_USX","flares":0,"source":null,"updated_at":null},{"quest":"S2_KAMINO_BORROW_USDG","flares":0,"source":null,"updated_at":null},{"quest":"S2_KAMINO_KVAULT_USDG_USX","flares":0,"source":null,"updated_at":null},{"quest":"S2_LOOPSCALE_SUPPLY_USX_ONE","flares":0,"source":null,"updated_at":null},{"quest":"S2_LOOPSCALE_BORROW_USX","flares":3062.146814413922,"source":"loopscale_event_integrated","updated_at":1778717872},{"quest":"S2_ORCA_USX_USDC","flares":0,"source":null,"updated_at":null},{"quest":"S2_ORCA_EUSX_USX","flares":0,"source":null,"updated_at":null},{"quest":"S2_ORCA_USX_USDG","flares":0,"source":null,"updated_at":null},{"quest":"S2_RAYDIUM_USX_USDC","flares":0,"source":null,"updated_at":null},{"quest":"S2_RAYDIUM_EUSX_USX","flares":0,"source":null,"updated_at":null},{"quest":"S2_REFERRAL_BONUS","flares":0.0,"source":"transform","updated_at":1778569930}],"evidence":{"S2_LOOPSCALE":{"extracted_at":1778597935,"type":"loopscale","positions":{"loopscale_supply_usx":0,"loopscale_borrow_usx":185.62},"events":[{"ts":1778351783,"ix":"createloan","pos_pubkey":"J4Wi4PqBT9k7QKFDqwUZxzX5RYJYv9d89NCq7UMBDjnd","sig":"3j7SLexj4DkR6R1LgVxMtUn1Fi9ZHCcAqC7i2JSCDYfr5btQZdK5TBydVz9KGdG7Xiy1PpA5xAHeA6DT7YvSvobW","deltas":[{"mint":"2u1tszSeqZ3qBWF3uNGPFc8TzMk2tdiwknnRMWGWjGWH","amt":90.66747599979863},{"mint":"6FrrzDk5mQARGc1TDYoyVnSyRdds1t4PbtohCD6p3tgG","amt":724.8141449997202},{"mint":"EPjFWdd5AufqSSqeM2qN1xzybapC8G4wEGGkZwyTDt1v","amt":724.711180000857}],"side":"borrow"}]}},"activity":[],"daily_emission_by_quest":{"S2_LOOPSCALE_BORROW_USX":185.62}}